files_to_claude_xml.py
files_to_claude_xml-2024.10.2.dist-info/LICENSE
files_to_claude_xml-2024.10.2.dist-info/METADATA
files_to_claude_xml-2024.10.2.dist-info/WHEEL
files_to_claude_xml-2024.10.2.dist-info/entry_points.txt
files_to_claude_xml-2024.10.2.dist-info/top_level.txt
files_to_claude_xml-2024.10.2.dist-info/RECORD
