Metadata-Version: 2.1
Name: files-to-claude-xml
Version: 2024.10.2
Summary: Use XML tags for long context prompting using Claude's multi-document structure.
Author: Jeff Triplett
License: PolyForm-Noncommercial-1.0.0 
Project-URL: Changelog, https://github.com/jefftriplett/files-to-claude-xml/releases
Project-URL: CI, https://github.com/jefftriplett/files-to-claude-xml/actions
Project-URL: Homepage, https://github.com/jefftriplett/files-to-claude-xml
Project-URL: Issues, https://github.com/jefftriplett/files-to-claude-xml/issues
Classifier: Development Status :: 3 - Alpha
Classifier: Programming Language :: Python :: 3.11
Classifier: Programming Language :: Python :: 3.12
Classifier: Programming Language :: Python :: 3.13
Requires-Python: >=3.11
License-File: LICENSE
Requires-Dist: rich
Requires-Dist: typer
